meena/__init__.py
meena/main.py
meena-0.0.8.dist-info/LICENSE.txt
meena-0.0.8.dist-info/METADATA
meena-0.0.8.dist-info/WHEEL
meena-0.0.8.dist-info/top_level.txt
meena-0.0.8.dist-info/RECORD
