Metadata-Version: 2.1
Name: meena
Version: 0.0.8
Summary: BUGGY ALPHA STAGE-CHILD:'tinda'
Home-page: UNKNOWN
Author: (Hank Singh)
Author-email: <hanksingh07@gmail.com>
License: UNKNOWN
Keywords: python
Platform: UNKNOWN
Classifier: Development Status :: 1 - Planning
Classifier: Programming Language :: Python :: 3
Classifier: Operating System :: Unix
Classifier: Operating System :: Microsoft :: Windows
License-File: LICENSE.txt
Requires-Dist: tinda
